RedisROS/Async_timer.py
RedisROS/Callback_groups.py
RedisROS/Config.py
RedisROS/Node.py
RedisROS/__init__.py
RedisROS/Endpoints/__init__.py
RedisROS/Endpoints/Core/Endpoint_abc.py
RedisROS/Endpoints/Core/__init__.py
RedisROS/Endpoints/Core/Publisher/Publisher.py
RedisROS/Endpoints/Core/Publisher/Publisher_module.py
RedisROS/Endpoints/Core/Publisher/__init__.py
RedisROS/Endpoints/Core/Shared_variable/Shared_variable.py
RedisROS/Endpoints/Core/Shared_variable/Shared_variable_module.py
RedisROS/Endpoints/Core/Shared_variable/__init__.py
RedisROS/Endpoints/Core/Subscriber/Subscriber.py
RedisROS/Endpoints/Core/Subscriber/Subscriber_module.py
RedisROS/Endpoints/Core/Subscriber/__init__.py
RedisROS/Endpoints/Core/Timer/Timer.py
RedisROS/Endpoints/Core/Timer/Timer_module.py
RedisROS/Endpoints/Core/Timer/__init__.py
RedisROS/Endpoints/Custom/__init__.py
RedisROS/Endpoints/Custom/ROS_Publisher/ROS_publisher_module.py
RedisROS/Endpoints/Custom/ROS_Publisher/__init__.py
RedisROS/Endpoints/Custom/ROS_Subscriber/ROS_subscriber_module.py
RedisROS/Endpoints/Custom/ROS_Subscriber/__init__.py
RedisROS/Nodes/Clock.py
RedisROS/Nodes/__init__.py
RedisROS-0.0.3.dist-info/LICENSE
RedisROS-0.0.3.dist-info/METADATA
RedisROS-0.0.3.dist-info/WHEEL
RedisROS-0.0.3.dist-info/top_level.txt
RedisROS-0.0.3.dist-info/RECORD
