Metadata-Version: 2.1
Name: RedisROS
Version: 0.0.3
Summary: A redis-based event-based ROS2-like library for python
Home-page: https://github.com/vguillet/RedisROS
Author: Victor Guillet
Author-email: victor.guillet@protonmail.com
License: GNU GPLv3
Keywords: ROS,ROS2,event-based,python,redis,robotics
Platform: UNKNOWN
Classifier: Development Status :: 3 - Alpha
Classifier: Intended Audience :: Developers
Classifier: Programming Language :: Python :: 3
Requires-Python: >= 3.8
Requires-Dist: redis
Requires-Dist: python-redis-lock
